<annotation>
	<folder>img</folder>
	<filename>IMG_20180522_125326.jpg</filename>
	<path>C:\detect4clover\img\IMG_20180522_125326.jpg</path>
	<source>
		<database>Unknown</database>
	</source>
	<size>
		<width>346</width>
		<height>576</height>
		<depth>3</depth>
	</size>
	<segmented>0</segmented>
	<object>
		<name>4leaf</name>
		<pose>Unspecified</pose>
		<truncated>0</truncated>
		<difficult>0</difficult>
		<bndbox>
			<xmin>135</xmin>
			<ymin>242</ymin>
			<xmax>184</xmax>
			<ymax>300</ymax>
		</bndbox>
	</object>
</annotation>
