<annotation>
	<folder>img</folder>
	<filename>IMG_20180628_125230.jpg</filename>
	<path>C:\detect4clover\img\IMG_20180628_125230.jpg</path>
	<source>
		<database>Unknown</database>
	</source>
	<size>
		<width>346</width>
		<height>576</height>
		<depth>3</depth>
	</size>
	<segmented>0</segmented>
	<object>
		<name>4leaf</name>
		<pose>Unspecified</pose>
		<truncated>0</truncated>
		<difficult>0</difficult>
		<bndbox>
			<xmin>139</xmin>
			<ymin>220</ymin>
			<xmax>286</xmax>
			<ymax>325</ymax>
		</bndbox>
	</object>
	<object>
		<name>4leaf</name>
		<pose>Unspecified</pose>
		<truncated>0</truncated>
		<difficult>0</difficult>
		<bndbox>
			<xmin>49</xmin>
			<ymin>355</ymin>
			<xmax>152</xmax>
			<ymax>449</ymax>
		</bndbox>
	</object>
	<object>
		<name>4leaf</name>
		<pose>Unspecified</pose>
		<truncated>0</truncated>
		<difficult>0</difficult>
		<bndbox>
			<xmin>163</xmin>
			<ymin>325</ymin>
			<xmax>278</xmax>
			<ymax>441</ymax>
		</bndbox>
	</object>
</annotation>
